[
    {
        "Radarly pid": 6127,
        "Radarly corpusId": 64143,
        "Radarly corpusName": "Feminine Care",
        "Product_Name": "Kotex靠得住 草本抑菌衛生棉 日用/夜用/護墊 19cm/23cm/28cm/35cm/17.5cm 現貨 蝦皮直送",
        "Product_url": "https://shopee.tw/product/37137599/777821120",
        "Status": "Historical",
        "Name": "b*****1",
        "Customer_Profile_Url": null,
        "Rating": 5,
        "TimeStamps": "2021-08-18 22:17 | 規格: 日用超薄23cm(15片x3包)/組",
        "Review": "",
        "Media_Url": [
            "https://play-ws.vod.shopee.com/api/v4/11110103/mms/tw_68f1ebd9-67cc-446d-9ae3-3d79906ab2f8_000021.default.mp4",
            "https://down-ws-in.img.susercontent.com/065fef90edc13abcd353bae4bd8a51a0.webp",
            "https://down-ws-in.img.susercontent.com/965d36bae34ae54768a9c1a194f2a91e.webp"
        ],
        "Likes": "有幫助的評價",
        "Id": ""
    },
    {
        "Radarly pid": 6127,
        "Radarly corpusId": 64143,
        "Radarly corpusName": "Feminine Care",
        "Product_Name": "Kotex靠得住 草本抑菌衛生棉 日用/夜用/護墊 19cm/23cm/28cm/35cm/17.5cm 現貨 蝦皮直送",
        "Product_url": "https://shopee.tw/product/37137599/777821120",
        "Status": "Historical",
        "Name": "l*****3",
        "Customer_Profile_Url": null,
        "Rating": 5,
        "TimeStamps": "2022-03-26 20:20 | 規格: [新包裝]夜超長35cm 8片X3包/組",
        "Review": "",
        "Media_Url": [
            "https://down-cvs-sg.vod.susercontent.com/api/v4/11110103/mms/tw_1f28b466-8dbd-436e-9b30-d3a352f27fb4_000047.default.mp4",
            "https://down-ws-in.img.susercontent.com/360f3eea9ec3525accc923b50c534b55.webp"
        ],
        "Likes": "有幫助的評價",
        "Id": ""
    },
    {
        "Radarly pid": 6127,
        "Radarly corpusId": 64143,
        "Radarly corpusName": "Feminine Care",
        "Product_Name": "Kotex靠得住 草本抑菌衛生棉 日用/夜用/護墊 19cm/23cm/28cm/35cm/17.5cm 現貨 蝦皮直送",
        "Product_url": "https://shopee.tw/product/37137599/777821120",
        "Status": "Historical",
        "Name": "l*****3",
        "Customer_Profile_Url": null,
        "Rating": 5,
        "TimeStamps": "2022-04-28 17:24 | 規格: [新包裝]夜超長35cm 8片X3包/組",
        "Review": "",
        "Media_Url": [
            "https://play-ws.vod.shopee.com/api/v4/11110103/mms/tw_29b36219-9f47-46d7-8538-5f9b417c501e_000051.default.mp4",
            "https://down-ws-in.img.susercontent.com/360f3eea9ec3525accc923b50c534b55.webp"
        ],
        "Likes": "有幫助的評價",
        "Id": ""
    },
    {
        "Radarly pid": 6127,
        "Radarly corpusId": 64143,
        "Radarly corpusName": "Feminine Care",
        "Product_Name": "Kotex靠得住 草本抑菌衛生棉 日用/夜用/護墊 19cm/23cm/28cm/35cm/17.5cm 現貨 蝦皮直送",
        "Product_url": "https://shopee.tw/product/37137599/777821120",
        "Status": "Historical",
        "Name": "h*****1",
        "Customer_Profile_Url": null,
        "Rating": 5,
        "TimeStamps": "2021-11-27 12:15 | 規格: 護墊17.5cm(24片X2包)/組",
        "Review": "",
        "Media_Url": [
            "https://play-ws.vod.shopee.com/api/v4/11110103/mms/tw_4915f405-ffbd-44ef-9bb8-6723502761aa_000033.default.mp4",
            "https://down-ws-in.img.susercontent.com/33c583893d02701c73aaf5d05cfe9ba1.webp"
        ],
        "Likes": "有幫助的評價",
        "Id": ""
    },
    {
        "Radarly pid": 6127,
        "Radarly corpusId": 64143,
        "Radarly corpusName": "Feminine Care",
        "Product_Name": "Kotex靠得住 草本抑菌衛生棉 日用/夜用/護墊 19cm/23cm/28cm/35cm/17.5cm 現貨 蝦皮直送",
        "Product_url": "https://shopee.tw/product/37137599/777821120",
        "Status": "Historical",
        "Name": "3*****y",
        "Customer_Profile_Url": null,
        "Rating": 5,
        "TimeStamps": "2022-11-16 18:43 | 規格: [新包裝]日薄23cm 14片X3包/組",
        "Review": "質地: 佳\n香味: 佳\n商品包裝精美，有泡泡棉保護，產品價錢CP值高，種類多元提供很多選擇，出貨很快速、品質優良賣家。\n",
        "Media_Url": [
            "https://down-gcp-sg.vod.susercontent.com/c3/98934353/103/A3oxOJgCAKQ=RAISEZEEACc.mp4",
            "https://down-ws-in.img.susercontent.com/tw-11134103-22110-z91soy7otyjvc1.webp"
        ],
        "Likes": "有幫助的評價",
        "Id": ""
    },
    {
        "Radarly pid": 6127,
        "Radarly corpusId": 64143,
        "Radarly corpusName": "Feminine Care",
        "Product_Name": "Kotex靠得住 草本抑菌衛生棉 日用/夜用/護墊 19cm/23cm/28cm/35cm/17.5cm 現貨 蝦皮直送",
        "Product_url": "https://shopee.tw/product/37137599/777821120",
        "Status": "Historical",
        "Name": "c*****j",
        "Customer_Profile_Url": null,
        "Rating": 5,
        "TimeStamps": "2022-04-22 14:06 | 規格: 護墊17.5cm(24片X2包)/組",
        "Review": "",
        "Media_Url": [
            "https://down-cvs-sg.vod.susercontent.com/c3/98934353/103/AnoyCUEAfAGpQQEhwgEAAEc.mp4",
            "https://down-ws-in.img.susercontent.com/2b06bcb433a5d191355da152b1df21ac.webp"
        ],
        "Likes": "有幫助的評價",
        "Id": ""
    },
    {
        "Radarly pid": 6127,
        "Radarly corpusId": 64143,
        "Radarly corpusName": "Feminine Care",
        "Product_Name": "Kotex靠得住 草本抑菌衛生棉 日用/夜用/護墊 19cm/23cm/28cm/35cm/17.5cm 現貨 蝦皮直送",
        "Product_url": "https://shopee.tw/product/37137599/777821120",
        "Status": "Historical",
        "Name": "l*****3",
        "Customer_Profile_Url": null,
        "Rating": 5,
        "TimeStamps": "2021-10-25 04:20 | 規格: [新包裝]夜超長35cm 8片X3包/組",
        "Review": "",
        "Media_Url": [
            "https://down-gcp-sg.vod.susercontent.com/api/v4/11110103/mms/tw_9c1809c1-0dc1-48f8-9add-beb855814d20_000029.default.mp4",
            "https://down-ws-in.img.susercontent.com/0a4f140d930d41c280da9ebce7381000.webp"
        ],
        "Likes": "有幫助的評價",
        "Id": ""
    },
    {
        "Radarly pid": 6127,
        "Radarly corpusId": 64143,
        "Radarly corpusName": "Feminine Care",
        "Product_Name": "Kotex靠得住 草本抑菌衛生棉 日用/夜用/護墊 19cm/23cm/28cm/35cm/17.5cm 現貨 蝦皮直送",
        "Product_url": "https://shopee.tw/product/37137599/777821120",
        "Status": "Historical",
        "Name": "p*****3",
        "Customer_Profile_Url": null,
        "Rating": 5,
        "TimeStamps": "2022-01-17 17:18 | 規格: [新包裝]夜薄28cm 12片x3包/組",
        "Review": "",
        "Media_Url": [
            "https://play-ws.vod.shopee.com/c3/98934353/103/Anoy1VUAaKZ2n=khOAEWAEc.mp4",
            "https://down-ws-in.img.susercontent.com/3aa4be7a6e2e5a03b0d5d989cfebdccd.webp"
        ],
        "Likes": "有幫助的評價",
        "Id": ""
    },
    {
        "Radarly pid": 6127,
        "Radarly corpusId": 64143,
        "Radarly corpusName": "Feminine Care",
        "Product_Name": "Kotex靠得住 草本抑菌衛生棉 日用/夜用/護墊 19cm/23cm/28cm/35cm/17.5cm 現貨 蝦皮直送",
        "Product_url": "https://shopee.tw/product/37137599/777821120",
        "Status": "Historical",
        "Name": "r*****m",
        "Customer_Profile_Url": null,
        "Rating": 5,
        "TimeStamps": "2022-03-19 08:03 | 規格: [新包裝]夜超長35cm 8片X3包/組",
        "Review": "",
        "Media_Url": [
            "https://play-ws.vod.shopee.com/c3/98934353/103/Anoyj3wAZAEQgP4hsAEJAEc.mp4",
            "https://down-ws-in.img.susercontent.com/e8e9ff8b6ae139e85e41a0eac2833cb9.webp"
        ],
        "Likes": "有幫助的評價",
        "Id": ""
    },
    {
        "Radarly pid": 6127,
        "Radarly corpusId": 64143,
        "Radarly corpusName": "Feminine Care",
        "Product_Name": "Kotex靠得住 草本抑菌衛生棉 日用/夜用/護墊 19cm/23cm/28cm/35cm/17.5cm 現貨 蝦皮直送",
        "Product_url": "https://shopee.tw/product/37137599/777821120",
        "Status": "Historical",
        "Name": "g*****8",
        "Customer_Profile_Url": null,
        "Rating": 5,
        "TimeStamps": "2021-11-17 15:30 | 規格: [新包裝]日薄23cm 14片X3包/組",
        "Review": "",
        "Media_Url": [
            "https://play-ws.vod.shopee.com/api/v4/11110103/mms/tw_8ae034bd-b096-4dd1-b042-f785e2eaa7df_000031.default.mp4",
            "https://down-ws-in.img.susercontent.com/241d60bab9fca6d88bfdea9048169802.webp",
            "https://down-ws-in.img.susercontent.com/2ae259a5c77f799a0d7bfb5d74c69a0c.webp"
        ],
        "Likes": "有幫助的評價",
        "Id": ""
    },
    {
        "Radarly pid": 6127,
        "Radarly corpusId": 64143,
        "Radarly corpusName": "Feminine Care",
        "Product_Name": "Kotex靠得住 草本抑菌衛生棉 日用/夜用/護墊 19cm/23cm/28cm/35cm/17.5cm 現貨 蝦皮直送",
        "Product_url": "https://shopee.tw/product/37137599/777821120",
        "Status": "Historical",
        "Name": "p*****1",
        "Customer_Profile_Url": null,
        "Rating": 5,
        "TimeStamps": "2022-10-07 20:46 | 規格: 日用 19cm 13片x3包/串",
        "Review": "",
        "Media_Url": [
            "https://play-ws.vod.shopee.com/api/v4/11110103/mms/tw_bb510bdc-b4b2-4ae4-bb24-03a7bfc78a1f_000072.12000051665155504.mp4",
            "https://down-ws-in.img.susercontent.com/tw-11134103-22100-ed4tj40oudiv60.webp",
            "https://down-ws-in.img.susercontent.com/tw-11134103-22100-hd4tj40oudiv4f.webp"
        ],
        "Likes": "有幫助的評價",
        "Id": ""
    },
    {
        "Radarly pid": 6127,
        "Radarly corpusId": 64143,
        "Radarly corpusName": "Feminine Care",
        "Product_Name": "Kotex靠得住 草本抑菌衛生棉 日用/夜用/護墊 19cm/23cm/28cm/35cm/17.5cm 現貨 蝦皮直送",
        "Product_url": "https://shopee.tw/product/37137599/777821120",
        "Status": "Historical",
        "Name": "s*****5",
        "Customer_Profile_Url": null,
        "Rating": 5,
        "TimeStamps": "2022-10-18 08:28 | 規格: 護墊17.5cm(24片X2包)/組",
        "Review": "香味: 還不錯，個人喜歡\n質地: 吸收力佳\n賣家出貨滿快的，日常消耗品，如果價格實惠用完應該會回購！長17.5公分用起來就是比較安心！\n",
        "Media_Url": [
            "https://play-ws.vod.shopee.com/api/v4/11110103/mms/tw_81e78eab-ffc7-4606-8eb2-7d7e4b3b3241_000074.12000461666061674.mp4",
            "https://down-ws-in.img.susercontent.com/tw-11134103-22100-q7dva7mltsivc1.webp"
        ],
        "Likes": "有幫助的評價",
        "Id": ""
    },
    {
        "Radarly pid": 6127,
        "Radarly corpusId": 64143,
        "Radarly corpusName": "Feminine Care",
        "Product_Name": "Kotex靠得住 草本抑菌衛生棉 日用/夜用/護墊 19cm/23cm/28cm/35cm/17.5cm 現貨 蝦皮直送",
        "Product_url": "https://shopee.tw/product/37137599/777821120",
        "Status": "Historical",
        "Name": "g*****6",
        "Customer_Profile_Url": null,
        "Rating": 5,
        "TimeStamps": "2022-11-15 17:12 | 規格: 日用 19cm 13片x3包/串",
        "Review": "質地: 清香\n香味: 茶樹\n感謝您好賣家。\n出貨迅速。\n商品無誤包裝完好無損。\n價格很優惠，一定會再回購。\n價格也比其他賣場便宜。\n",
        "Media_Url": [
            "https://play-ws.vod.shopee.com/c3/98934353/103/A3oxOI0uAATmY-wREZkIACc.mp4",
            "https://down-ws-in.img.susercontent.com/tw-11134103-22110-483kk625axjvb3.webp"
        ],
        "Likes": "有幫助的評價",
        "Id": ""
    },
    {
        "Radarly pid": 6127,
        "Radarly corpusId": 64143,
        "Radarly corpusName": "Feminine Care",
        "Product_Name": "Kotex靠得住 草本抑菌衛生棉 日用/夜用/護墊 19cm/23cm/28cm/35cm/17.5cm 現貨 蝦皮直送",
        "Product_url": "https://shopee.tw/product/37137599/777821120",
        "Status": "Historical",
        "Name": "a*****o",
        "Customer_Profile_Url": null,
        "Rating": 5,
        "TimeStamps": "2023-01-25 20:18 | 規格: [新包裝]日薄23cm 14片X3包/組",
        "Review": "質地: 好\n香味: 好\n這個商品真的很讚，物美價廉，CP值高，下次還會再回購，感謝賣家提供優質商品供選購，謝謝。\n",
        "Media_Url": [
            "https://play-ws.vod.shopee.com/api/v4/11110103/mms/tw_61d4d8db-9f20-4005-8097-569d5411fead_000089.16000051674658044.mp4",
            "https://down-ws-in.img.susercontent.com/tw-11134103-23010-nj6ihi6vtqmv16.webp"
        ],
        "Likes": "有幫助的評價",
        "Id": ""
    },
    {
        "Radarly pid": 6127,
        "Radarly corpusId": 64143,
        "Radarly corpusName": "Feminine Care",
        "Product_Name": "Kotex靠得住 草本抑菌衛生棉 日用/夜用/護墊 19cm/23cm/28cm/35cm/17.5cm 現貨 蝦皮直送",
        "Product_url": "https://shopee.tw/product/37137599/777821120",
        "Status": "Historical",
        "Name": "j*****2",
        "Customer_Profile_Url": null,
        "Rating": 5,
        "TimeStamps": "2022-02-03 16:53 | 規格: [新包裝]日薄23cm 14片X3包/組",
        "Review": "",
        "Media_Url": [
            "https://down-gcp-sg.vod.susercontent.com/c3/98934353/103/Anoyy30AICtG=fohsQEPAEc.mp4",
            "https://down-ws-in.img.susercontent.com/38bc693d32e456487bb40be131b82cfb.webp"
        ],
        "Likes": "有幫助的評價",
        "Id": ""
    },
    {
        "Radarly pid": 6127,
        "Radarly corpusId": 64143,
        "Radarly corpusName": "Feminine Care",
        "Product_Name": "Kotex靠得住 草本抑菌衛生棉 日用/夜用/護墊 19cm/23cm/28cm/35cm/17.5cm 現貨 蝦皮直送",
        "Product_url": "https://shopee.tw/product/37137599/777821120",
        "Status": "Historical",
        "Name": "f*****e",
        "Customer_Profile_Url": null,
        "Rating": 5,
        "TimeStamps": "2021-10-21 11:07 | 規格: [新包裝]夜薄28cm 12片x3包/組",
        "Review": "",
        "Media_Url": [
            "https://play-ws.vod.shopee.com/api/v4/11110103/mms/tw_742fe1a5-a5a8-447b-859c-2c398f3642b9_000028.default.mp4",
            "https://down-ws-in.img.susercontent.com/bcdc307221e3a517e1ae4aff6c5f2a35.webp",
            "https://down-ws-in.img.susercontent.com/0fd407387c004c2803f1fcff74f8e9ef.webp",
            "https://down-ws-in.img.susercontent.com/ee9e913f53eee842f4772728536fae0c.webp"
        ],
        "Likes": "有幫助的評價",
        "Id": ""
    },
    {
        "Radarly pid": 6127,
        "Radarly corpusId": 64143,
        "Radarly corpusName": "Feminine Care",
        "Product_Name": "Kotex靠得住 草本抑菌衛生棉 日用/夜用/護墊 19cm/23cm/28cm/35cm/17.5cm 現貨 蝦皮直送",
        "Product_url": "https://shopee.tw/product/37137599/777821120",
        "Status": "Historical",
        "Name": "g*****6",
        "Customer_Profile_Url": null,
        "Rating": 5,
        "TimeStamps": "2022-04-05 17:53 | 規格: [新包裝]夜薄28cm 12片x3包/組",
        "Review": "",
        "Media_Url": [
            "https://down-cvs-sg.vod.susercontent.com/api/v4/11110103/mms/tw_6b6c937d-bb75-4ab6-8e40-201380cc6446_000048.default.mp4",
            "https://down-ws-in.img.susercontent.com/82f97ecd0728555d691005c510e55c50.webp"
        ],
        "Likes": "有幫助的評價",
        "Id": ""
    },
    {
        "Radarly pid": 6127,
        "Radarly corpusId": 64143,
        "Radarly corpusName": "Feminine Care",
        "Product_Name": "Kotex靠得住 草本抑菌衛生棉 日用/夜用/護墊 19cm/23cm/28cm/35cm/17.5cm 現貨 蝦皮直送",
        "Product_url": "https://shopee.tw/product/37137599/777821120",
        "Status": "Historical",
        "Name": "m*****1",
        "Customer_Profile_Url": null,
        "Rating": 5,
        "TimeStamps": "2022-10-22 18:48 | 規格: [新包裝]日薄23cm 14片X3包/組",
        "Review": "質地: 不錯\n香味: 無\n網上購物這麼激烈，沒想到店家的服務這麼好，商品質量好而價低廉， 很熱情的賣家\n",
        "Media_Url": [
            "https://play-ws.vod.shopee.com/c3/98934353/103/A3oxOCLlAEDAUP8PEXUFACc.mp4",
            "https://down-ws-in.img.susercontent.com/tw-11134103-22100-ulwy7yi95yivfd.webp"
        ],
        "Likes": "有幫助的評價",
        "Id": ""
    },
    {
        "Radarly pid": 6127,
        "Radarly corpusId": 64143,
        "Radarly corpusName": "Feminine Care",
        "Product_Name": "Kotex靠得住 草本抑菌衛生棉 日用/夜用/護墊 19cm/23cm/28cm/35cm/17.5cm 現貨 蝦皮直送",
        "Product_url": "https://shopee.tw/product/37137599/777821120",
        "Status": "Historical",
        "Name": "t*****6",
        "Customer_Profile_Url": null,
        "Rating": 5,
        "TimeStamps": "2022-12-20 19:09 | 規格: [新包裝]夜超長35cm 8片X3包/組",
        "Review": "質地: 柔軟\n香味: 無\n都用這款衛生棉，好用便宜柔軟不磨大腿，三包一組是最划算的價位，數量正確包裝完整，值得推薦的商品跟賣家。\n",
        "Media_Url": [
            "https://down-cvs-sg.vod.susercontent.com/api/v4/11110103/mms/tw_9e4d26ad-b26a-4063-85a9-c4ff6a420101_000084.16000051671543230.mp4",
            "https://down-ws-in.img.susercontent.com/tw-11134103-22120-pa1p1p9hdblvb5.webp"
        ],
        "Likes": "有幫助的評價",
        "Id": ""
    },
    {
        "Radarly pid": 6127,
        "Radarly corpusId": 64143,
        "Radarly corpusName": "Feminine Care",
        "Product_Name": "Kotex靠得住 草本抑菌衛生棉 日用/夜用/護墊 19cm/23cm/28cm/35cm/17.5cm 現貨 蝦皮直送",
        "Product_url": "https://shopee.tw/product/37137599/777821120",
        "Status": "Historical",
        "Name": "a*****5",
        "Customer_Profile_Url": null,
        "Rating": 5,
        "TimeStamps": "2022-02-28 14:13 | 規格: [新包裝]夜薄28cm 12片x3包/組",
        "Review": "",
        "Media_Url": [
            "https://play-ws.vod.shopee.com/api/v4/11110103/mms/tw_5148dccc-16eb-4f40-8f0e-0f4c7358544b_000043.default.mp4",
            "https://down-ws-in.img.susercontent.com/74875c760b7a2c4466dcf932e43818e4.webp"
        ],
        "Likes": "有幫助的評價",
        "Id": ""
    },
    {
        "Radarly pid": 6127,
        "Radarly corpusId": 64143,
        "Radarly corpusName": "Feminine Care",
        "Product_Name": "Kotex靠得住 草本抑菌衛生棉 日用/夜用/護墊 19cm/23cm/28cm/35cm/17.5cm 現貨 蝦皮直送",
        "Product_url": "https://shopee.tw/product/37137599/777821120",
        "Status": "Historical",
        "Name": "a*****5",
        "Customer_Profile_Url": null,
        "Rating": 5,
        "TimeStamps": "2022-12-21 14:58 | 規格: [新包裝]夜超長35cm 8片X3包/組",
        "Review": "",
        "Media_Url": [
            "https://play-ws.vod.shopee.com/api/v4/11110103/mms/tw_835523ee-0b11-4da6-a42f-d0cae545f732_000084.16000051671614825.mp4",
            "https://down-ws-in.img.susercontent.com/tw-11134103-22120-1z93nxy3jclvfd.webp"
        ],
        "Likes": "有幫助的評價",
        "Id": ""
    },
    {
        "Radarly pid": 6127,
        "Radarly corpusId": 64143,
        "Radarly corpusName": "Feminine Care",
        "Product_Name": "Kotex靠得住 草本抑菌衛生棉 日用/夜用/護墊 19cm/23cm/28cm/35cm/17.5cm 現貨 蝦皮直送",
        "Product_url": "https://shopee.tw/product/37137599/777821120",
        "Status": "Historical",
        "Name": "l*****i",
        "Customer_Profile_Url": null,
        "Rating": 5,
        "TimeStamps": "2021-10-28 18:32 | 規格: [新包裝]夜超長35cm 8片X3包/組",
        "Review": "",
        "Media_Url": [
            "https://down-cvs-sg.vod.susercontent.com/api/v4/11110103/mms/tw_e22ceb81-c0df-44f3-b282-2aba53ec9f22_000029.default.mp4",
            "https://down-ws-in.img.susercontent.com/c02623749936198551bb374abf68ed57.webp"
        ],
        "Likes": "有幫助的評價",
        "Id": ""
    },
    {
        "Radarly pid": 6127,
        "Radarly corpusId": 64143,
        "Radarly corpusName": "Feminine Care",
        "Product_Name": "Kotex靠得住 草本抑菌衛生棉 日用/夜用/護墊 19cm/23cm/28cm/35cm/17.5cm 現貨 蝦皮直送",
        "Product_url": "https://shopee.tw/product/37137599/777821120",
        "Status": "Historical",
        "Name": "c*****9",
        "Customer_Profile_Url": null,
        "Rating": 5,
        "TimeStamps": "2021-01-19 05:59 | 規格: 夜用超薄28cm(13片x3包)/組",
        "Review": "",
        "Media_Url": [
            "https://play-ws.vod.shopee.com/s4/98934353/10321011908/czQsc2V0NS0xMTIyLDEzNTEzMjU4NDcwMzg4MDgwNjQsMQ.mp4",
            "https://down-ws-in.img.susercontent.com/33c33f8c97a32eccc9a8f2cd7f20c053.webp"
        ],
        "Likes": "有幫助的評價",
        "Id": ""
    },
    {
        "Radarly pid": 6127,
        "Radarly corpusId": 64143,
        "Radarly corpusName": "Feminine Care",
        "Product_Name": "Kotex靠得住 草本抑菌衛生棉 日用/夜用/護墊 19cm/23cm/28cm/35cm/17.5cm 現貨 蝦皮直送",
        "Product_url": "https://shopee.tw/product/37137599/777821120",
        "Status": "Historical",
        "Name": "l*****5",
        "Customer_Profile_Url": null,
        "Rating": 5,
        "TimeStamps": "2021-02-05 06:57 | 規格: 夜用超長35cm(9片x3包)/組",
        "Review": "",
        "Media_Url": [
            "https://play-ws.vod.shopee.com/api/v4/11110103/mms/tw_8552eed0-97e4-4900-97c0-5db32408d804_000004.default.mp4",
            "https://down-ws-in.img.susercontent.com/f27ededf04b9d4d5be00abffef283b6f.webp"
        ],
        "Likes": "有幫助的評價",
        "Id": ""
    },
    {
        "Radarly pid": 6127,
        "Radarly corpusId": 64143,
        "Radarly corpusName": "Feminine Care",
        "Product_Name": "Kotex靠得住 草本抑菌衛生棉 日用/夜用/護墊 19cm/23cm/28cm/35cm/17.5cm 現貨 蝦皮直送",
        "Product_url": "https://shopee.tw/product/37137599/777821120",
        "Status": "Historical",
        "Name": "k*****0",
        "Customer_Profile_Url": null,
        "Rating": 5,
        "TimeStamps": "2021-07-16 20:40 | 規格: 夜用超長35cm(9片x3包)/組",
        "Review": "",
        "Media_Url": [
            "https://play-ws.vod.shopee.com/api/v4/11110103/mms/tw_dbe48d5f-e3cd-478e-84f9-55161f3047e7_000018.default.mp4",
            "https://down-ws-in.img.susercontent.com/8aad43479c2b603c4df81b757ad420ab.webp"
        ],
        "Likes": "有幫助的評價",
        "Id": ""
    },
    {
        "Radarly pid": 6127,
        "Radarly corpusId": 64143,
        "Radarly corpusName": "Feminine Care",
        "Product_Name": "Kotex靠得住 草本抑菌衛生棉 日用/夜用/護墊 19cm/23cm/28cm/35cm/17.5cm 現貨 蝦皮直送",
        "Product_url": "https://shopee.tw/product/37137599/777821120",
        "Status": "Historical",
        "Name": "a*****6",
        "Customer_Profile_Url": null,
        "Rating": 5,
        "TimeStamps": "2021-02-05 17:38 | 規格: 夜用超薄28cm(13片x3包)/組",
        "Review": "",
        "Media_Url": [
            "https://down-cvs-sg.vod.susercontent.com/api/v4/11110103/mms/tw_37fc4fbc-fea0-4fed-84f3-69caaa47b42b_000013.default.mp4",
            "https://down-ws-in.img.susercontent.com/515f6d60c08acb5598b083e1650d6088.webp"
        ],
        "Likes": "有幫助的評價",
        "Id": ""
    },
    {
        "Radarly pid": 6127,
        "Radarly corpusId": 64143,
        "Radarly corpusName": "Feminine Care",
        "Product_Name": "Kotex靠得住 草本抑菌衛生棉 日用/夜用/護墊 19cm/23cm/28cm/35cm/17.5cm 現貨 蝦皮直送",
        "Product_url": "https://shopee.tw/product/37137599/777821120",
        "Status": "Historical",
        "Name": "c*****5",
        "Customer_Profile_Url": null,
        "Rating": 5,
        "TimeStamps": "2022-11-22 19:21 | 規格: 日用 19cm 13片x3包/串",
        "Review": "質地: 好\n東西收到，包裝良好沒有缺損，商品都是需要用到所以補貨的，又有10%的蝦幣回饋，很划算有需要會再回購\n",
        "Media_Url": [
            "https://down-gcp-sg.vod.susercontent.com/c3/98934353/103/A3oxOL66AKiSZX4SEZwAACc.mp4",
            "https://down-ws-in.img.susercontent.com/tw-11134103-22110-ulg7lbbcf8jv2e.webp"
        ],
        "Likes": "1",
        "Id": ""
    },
    {
        "Radarly pid": 6127,
        "Radarly corpusId": 64143,
        "Radarly corpusName": "Feminine Care",
        "Product_Name": "Kotex靠得住 草本抑菌衛生棉 日用/夜用/護墊 19cm/23cm/28cm/35cm/17.5cm 現貨 蝦皮直送",
        "Product_url": "https://shopee.tw/product/37137599/777821120",
        "Status": "Historical",
        "Name": "5*****d",
        "Customer_Profile_Url": null,
        "Rating": 5,
        "TimeStamps": "2021-03-30 20:48 | 規格: 夜用超薄28cm(13片x3包)/組",
        "Review": "",
        "Media_Url": [
            "https://down-gcp-sg.vod.susercontent.com/api/v4/11110103/mms/tw_2883044d-c2ec-45f1-8029-821b249d6da9_000006.default.mp4",
            "https://down-ws-in.img.susercontent.com/fe952cba5c4e6fc51aba2fd0b5e12c70.webp"
        ],
        "Likes": "有幫助的評價",
        "Id": ""
    },
    {
        "Radarly pid": 6127,
        "Radarly corpusId": 64143,
        "Radarly corpusName": "Feminine Care",
        "Product_Name": "Kotex靠得住 草本抑菌衛生棉 日用/夜用/護墊 19cm/23cm/28cm/35cm/17.5cm 現貨 蝦皮直送",
        "Product_url": "https://shopee.tw/product/37137599/777821120",
        "Status": "Historical",
        "Name": "p*****1",
        "Customer_Profile_Url": null,
        "Rating": 5,
        "TimeStamps": "2021-06-13 22:30 | 規格: 日用超薄23cm(15片x3包)/組",
        "Review": "",
        "Media_Url": [
            "https://down-gcp-sg.vod.susercontent.com/api/v4/11110103/mms/tw_269926e3-1b72-4106-96d7-3f98f7ec5685_000011.default.mp4",
            "https://down-ws-in.img.susercontent.com/7a78d6e05724a18bf601ad3382ac8c3a.webp"
        ],
        "Likes": "有幫助的評價",
        "Id": ""
    },
    {
        "Radarly pid": 6127,
        "Radarly corpusId": 64143,
        "Radarly corpusName": "Feminine Care",
        "Product_Name": "Kotex靠得住 草本抑菌衛生棉 日用/夜用/護墊 19cm/23cm/28cm/35cm/17.5cm 現貨 蝦皮直送",
        "Product_url": "https://shopee.tw/product/37137599/777821120",
        "Status": "Historical",
        "Name": "v*****0",
        "Customer_Profile_Url": null,
        "Rating": 5,
        "TimeStamps": "2021-08-16 22:48 | 規格: 護墊17.5cm(24片X2包)/組",
        "Review": "",
        "Media_Url": [
            "https://play-ws.vod.shopee.com/api/v4/11110103/mms/tw_3dffe775-5074-4b7f-8a08-149855624e06_000021.default.mp4",
            "https://down-ws-in.img.susercontent.com/50b3e9257581dc2a721cfac88bf78282.webp"
        ],
        "Likes": "有幫助的評價",
        "Id": ""
    },
    {
        "Radarly pid": 6127,
        "Radarly corpusId": 64143,
        "Radarly corpusName": "Feminine Care",
        "Product_Name": "Kotex靠得住 草本抑菌衛生棉 日用/夜用/護墊 19cm/23cm/28cm/35cm/17.5cm 現貨 蝦皮直送",
        "Product_url": "https://shopee.tw/product/37137599/777821120",
        "Status": "Historical",
        "Name": "c*****8",
        "Customer_Profile_Url": null,
        "Rating": 5,
        "TimeStamps": "2021-06-24 15:47 | 規格: 護墊17.5cm(24片X2包)/組",
        "Review": "",
        "Media_Url": [
            "https://down-gcp-sg.vod.susercontent.com/api/v4/11110103/mms/tw_cffd7613-6851-4b48-b493-d81f218dbe69_000015.default.mp4",
            "https://down-ws-in.img.susercontent.com/c0c71b2e867b08bb80cce582c3b922a5.webp"
        ],
        "Likes": "有幫助的評價",
        "Id": ""
    },
    {
        "Radarly pid": 6127,
        "Radarly corpusId": 64143,
        "Radarly corpusName": "Feminine Care",
        "Product_Name": "Kotex靠得住 草本抑菌衛生棉 日用/夜用/護墊 19cm/23cm/28cm/35cm/17.5cm 現貨 蝦皮直送",
        "Product_url": "https://shopee.tw/product/37137599/777821120",
        "Status": "Historical",
        "Name": "g*****7",
        "Customer_Profile_Url": null,
        "Rating": 5,
        "TimeStamps": "2021-03-23 10:31 | 規格: 夜用超長35cm(9片x3包)/組",
        "Review": "",
        "Media_Url": [
            "https://play-ws.vod.shopee.com/api/v4/11110103/mms/tw_b6a05bb2-b709-4eec-a2aa-9def0bc99c29_000006.default.mp4",
            "https://down-ws-in.img.susercontent.com/f9f2df39841b845fae1d5092565c3ddf.webp"
        ],
        "Likes": "有幫助的評價",
        "Id": ""
    },
    {
        "Radarly pid": 6127,
        "Radarly corpusId": 64143,
        "Radarly corpusName": "Feminine Care",
        "Product_Name": "Kotex靠得住 草本抑菌衛生棉 日用/夜用/護墊 19cm/23cm/28cm/35cm/17.5cm 現貨 蝦皮直送",
        "Product_url": "https://shopee.tw/product/37137599/777821120",
        "Status": "Historical",
        "Name": "o*****4",
        "Customer_Profile_Url": null,
        "Rating": 5,
        "TimeStamps": "2021-11-30 09:41 | 規格: [新包裝]夜薄28cm 12片x3包/組",
        "Review": "",
        "Media_Url": [
            "https://down-gcp-sg.vod.susercontent.com/api/v4/11110103/mms/tw_46327720-29d9-41d4-bcde-45f845bc73fa_000033.default.mp4",
            "https://down-ws-in.img.susercontent.com/a2e06705e8e0d40032386c6ab1216d55.webp"
        ],
        "Likes": "有幫助的評價",
        "Id": ""
    },
    {
        "Radarly pid": 6127,
        "Radarly corpusId": 64143,
        "Radarly corpusName": "Feminine Care",
        "Product_Name": "Kotex靠得住 草本抑菌衛生棉 日用/夜用/護墊 19cm/23cm/28cm/35cm/17.5cm 現貨 蝦皮直送",
        "Product_url": "https://shopee.tw/product/37137599/777821120",
        "Status": "Historical",
        "Name": "a*****w",
        "Customer_Profile_Url": null,
        "Rating": 5,
        "TimeStamps": "2021-12-07 13:52 | 規格: [新包裝]日薄23cm 14片X3包/組",
        "Review": "",
        "Media_Url": [
            "https://play-ws.vod.shopee.com/api/v4/11110103/mms/tw_fe04b196-edc2-4eda-9027-9cbc424dfe2b_000034.default.mp4",
            "https://down-ws-in.img.susercontent.com/87ab19d00d5597fa93337208a780026b.webp"
        ],
        "Likes": "有幫助的評價",
        "Id": ""
    },
    {
        "Radarly pid": 6127,
        "Radarly corpusId": 64143,
        "Radarly corpusName": "Feminine Care",
        "Product_Name": "Kotex靠得住 草本抑菌衛生棉 日用/夜用/護墊 19cm/23cm/28cm/35cm/17.5cm 現貨 蝦皮直送",
        "Product_url": "https://shopee.tw/product/37137599/777821120",
        "Status": "Historical",
        "Name": "c*****9",
        "Customer_Profile_Url": null,
        "Rating": 5,
        "TimeStamps": "2021-04-07 15:53 | 規格: 日用超薄23cm(15片x3包)/組",
        "Review": "",
        "Media_Url": [
            "https://play-ws.vod.shopee.com/api/v4/11110103/mms/tw_4767c9e2-b20d-4447-9f52-c38847b400f9_000007.default.mp4",
            "https://down-ws-in.img.susercontent.com/adc0d73776dee71877934b543d0d0c1b.webp"
        ],
        "Likes": "有幫助的評價",
        "Id": ""
    },
    {
        "Radarly pid": 6127,
        "Radarly corpusId": 64143,
        "Radarly corpusName": "Feminine Care",
        "Product_Name": "Kotex靠得住 草本抑菌衛生棉 日用/夜用/護墊 19cm/23cm/28cm/35cm/17.5cm 現貨 蝦皮直送",
        "Product_url": "https://shopee.tw/product/37137599/777821120",
        "Status": "Historical",
        "Name": "c*****9",
        "Customer_Profile_Url": null,
        "Rating": 5,
        "TimeStamps": "2021-01-21 17:27 | 規格: 日用超薄23cm(15片x3包)/組",
        "Review": "",
        "Media_Url": [
            "https://play-ws.vod.shopee.com/api/v4/11110103/mms/tw_8b6ec0ae-117d-4f1f-92a1-18ba15035068_000003.default.mp4",
            "https://down-ws-in.img.susercontent.com/4696767495c7093070c20a5be453f962.webp"
        ],
        "Likes": "有幫助的評價",
        "Id": ""
    }
]